MatrixChatbotGenerator/__init__.py
MatrixChatbotGenerator/call_user_interface.py
MatrixChatbotGenerator/run_flask_app.py
MatrixChatbotGenerator/run_quizbot.py
MatrixChatbotGenerator/setup_db.py
MatrixChatbotGenerator/start_user_interface.py
MatrixChatbotGenerator/classes/ChatbotConfig.py
MatrixChatbotGenerator/classes/ChatbotGenerator.py
MatrixChatbotGenerator/classes/ConfigManager.py
MatrixChatbotGenerator/classes/QTIParser.py
MatrixChatbotGenerator/classes/QuizBot.py
MatrixChatbotGenerator/classes/__init__.py
MatrixChatbotGenerator/store/__init__.py
MatrixChatbotGenerator/store/db_config.py
MatrixChatbotGenerator/store/db_operations.py
MatrixChatbotGenerator/store/db_test.py
MatrixChatbotGenerator/store/flask_app.py
MatrixChatbotGenerator/store/init_db.py
MatrixChatbotGenerator/store/models.py
MatrixChatbotGenerator/store/recreate_db.py
MatrixChatbotGenerator/structures/__init__.py
MatrixChatbotGenerator/structures/answer.py
MatrixChatbotGenerator/structures/feedback.py
MatrixChatbotGenerator/structures/question.py
MatrixChatbotGenerator/structures/quiz.py
MatrixChatbotGenerator/ui/ConfigWindow.py
MatrixChatbotGenerator/ui/QuizWindow.py
MatrixChatbotGenerator/ui/QuizzesWindow.py
MatrixChatbotGenerator/ui/UserInterface.py
MatrixChatbotGenerator/ui/__init__.py
MatrixChatbotGenerator/util/__init__.py
MatrixChatbotGenerator/util/http_handler.py
MatrixChatbotGenerator/util/utility_functions.py
mci_dibse_lt2713_matrix_chatbot_generator-1.0.5.dist-info/METADATA
mci_dibse_lt2713_matrix_chatbot_generator-1.0.5.dist-info/WHEEL
mci_dibse_lt2713_matrix_chatbot_generator-1.0.5.dist-info/top_level.txt
mci_dibse_lt2713_matrix_chatbot_generator-1.0.5.dist-info/RECORD
