Metadata-Version: 2.1
Name: mci-dibse-lt2713-matrix-chatbot-generator
Version: 1.0.5
Summary: Package to create a Matrix Chatbot
Home-page: UNKNOWN
Author: Tobias Leiter
Author-email: lt2713@mci4me.at
License: UNKNOWN
Platform: UNKNOWN
Classifier: Programming Language :: Python :: 3
Classifier: License :: OSI Approved :: MIT License
Classifier: Operating System :: OS Independent
